html2pdf_bookdown/__init__.py
html2pdf_bookdown/__main__.py
html2pdf_bookdown/convert.py
html2pdf_bookdown/fetch.py
html2pdf_bookdown-0.1.1.dist-info/LICENSE
html2pdf_bookdown-0.1.1.dist-info/METADATA
html2pdf_bookdown-0.1.1.dist-info/WHEEL
html2pdf_bookdown-0.1.1.dist-info/entry_points.txt
html2pdf_bookdown-0.1.1.dist-info/top_level.txt
html2pdf_bookdown-0.1.1.dist-info/RECORD
