Metadata-Version: 2.1
Name: html2pdf-bookdown
Version: 0.1.1
Summary: Fetch and convert HTML to PDF for eBooks published with Bookdown
Home-page: https://github.com/caizefeng/html2pdf_bookdown
Author: Zavier Cai
Author-email: caizefeng18@gmail.com
License: MIT
Keywords: html pdf conversion bookdown
Platform: UNKNOWN
Classifier: License :: OSI Approved :: MIT License
Classifier: Operating System :: OS Independent
Classifier: Programming Language :: Python :: 3
Requires-Python: >=3.6
License-File: LICENSE
Requires-Dist: setuptools
Requires-Dist: requests
Requires-Dist: beautifulsoup4
Requires-Dist: PyPDF2
Requires-Dist: selenium
Requires-Dist: tqdm
